{
  "db_name": "PostgreSQL",
  "query": "\n            INSERT INTO \"tag\" (name, public_id)\n            VALUES ($1, $2)\n            RETURNING *\n            ",
  "describe": {
    "columns": [
      {
        "ordinal": 0,
        "name": "id",
        "type_info": "Int4"
      },
      {
        "ordinal": 1,
        "name": "public_id",
        "type_info": "Text"
      },
      {
        "ordinal": 2,
        "name": "name",
        "type_info": "Text"
      }
    ],
    "parameters": {
      "Left": [
        "Text",
        "Text"
      ]
    },
    "nullable": [
      false,
      false,
      false
    ]
  },
  "hash": "3712b4ba3c5320896b9a5f80508437d37f645d1bced462c2656bff8d1f04ec69"
}
